simple_file_sorter/__init__.py
simple_file_sorter/core.py
simple_file_sorter-0.1.2.dist-info/entry_points.txt
simple_file_sorter-0.1.2.dist-info/WHEEL
simple_file_sorter-0.1.2.dist-info/METADATA
simple_file_sorter-0.1.2.dist-info/RECORD
