Metadata-Version: 2.1
Name: simple-file-sorter
Version: 0.1.2
Summary: Simple File Sorter
Home-page: https://github.com/moskrc/filesorter
Keywords: sort,file_sorter,file,sorter
Author: Vitalii Shishorin
Author-email: moskrc@gmail.com
Requires-Python: >=3.9,<4.0
Classifier: Programming Language :: Python :: 3
Classifier: Programming Language :: Python :: 3.9
Classifier: Programming Language :: Python :: 3.10
Classifier: Programming Language :: Python :: 3.11
Project-URL: Repository, https://github.com/moskrc/filesorter
